README.txt
setup.cfg
setup.py
appium_selector/DeviceSelector.py
appium_selector/FilePath.py
appium_selector/__init__.py
appium_selector.egg-info/PKG-INFO
appium_selector.egg-info/SOURCES.txt
appium_selector.egg-info/dependency_links.txt
appium_selector.egg-info/requires.txt
appium_selector.egg-info/top_level.txt